swapnil_mcp_web_extractor-0.0.9.dist-info/licenses/LICENSE
web_extractor/__init__.py
web_extractor/__main__.py
web_extractor/server.py
swapnil_mcp_web_extractor-0.0.9.dist-info/METADATA
swapnil_mcp_web_extractor-0.0.9.dist-info/WHEEL
swapnil_mcp_web_extractor-0.0.9.dist-info/entry_points.txt
swapnil_mcp_web_extractor-0.0.9.dist-info/top_level.txt
swapnil_mcp_web_extractor-0.0.9.dist-info/RECORD
