Metadata-Version: 2.4
Name: swapnil-mcp-web-extractor
Version: 0.0.9
Summary: MCP server that extracts content from web pages for LLMs
Author-email: swapnil dagade <swapnildagade@gmail.com>
License: MIT
Classifier: Programming Language :: Python :: 3
Classifier: License :: OSI Approved :: MIT License
Classifier: Operating System :: OS Independent
Requires-Python: >=3.9
License-File: LICENSE
Requires-Dist: mcp>=1.2.0
Requires-Dist: requests
Requires-Dist: beautifulsoup4
Dynamic: license-file
